NetkillerArchitectFix1/README.md
NetkillerArchitectFix1/__init__.py
NetkillerArchitectFix1/__main__.py
NetkillerArchitectFix1/file.epub
NetkillerArchitectFix1/index.html
NetkillerArchitectFix1/css/__init__.py
NetkillerArchitectFix1/css/annotations.css
NetkillerArchitectFix1/css/main.css
NetkillerArchitectFix1/css/normalize.css
NetkillerArchitectFix1/css/popup.css
NetkillerArchitectFix1/font/__init__.py
NetkillerArchitectFix1/font/fontello.eot
NetkillerArchitectFix1/font/fontello.svg
NetkillerArchitectFix1/font/fontello.ttf
NetkillerArchitectFix1/font/fontello.woff
NetkillerArchitectFix1/img/__init__.py
NetkillerArchitectFix1/img/annotator-glyph-sprite.png
NetkillerArchitectFix1/img/annotator-icon-sprite.png
NetkillerArchitectFix1/img/apple-touch-icon.png
NetkillerArchitectFix1/img/cancelfullscreen.png
NetkillerArchitectFix1/img/close.png
NetkillerArchitectFix1/img/fullscreen.png
NetkillerArchitectFix1/img/loader.gif
NetkillerArchitectFix1/img/menu-icon.png
NetkillerArchitectFix1/img/save.png
NetkillerArchitectFix1/img/saved.png
NetkillerArchitectFix1/img/settings-s.png
NetkillerArchitectFix1/img/settings.png
NetkillerArchitectFix1/img/star.png
NetkillerArchitectFix1/js/__init__.py
NetkillerArchitectFix1/js/epub.js
NetkillerArchitectFix1/js/epub.min.js
NetkillerArchitectFix1/js/epub.min.map
NetkillerArchitectFix1/js/hooks.min.js
NetkillerArchitectFix1/js/hooks.min.map
NetkillerArchitectFix1/js/reader.js
NetkillerArchitectFix1/js/reader.js.map
NetkillerArchitectFix1/js/reader.min.js
NetkillerArchitectFix1/js/reader.min.map
NetkillerArchitectFix1/js/hooks/__init__.py
NetkillerArchitectFix1/js/hooks/extensions/__init__.py
NetkillerArchitectFix1/js/hooks/extensions/highlight.js
NetkillerArchitectFix1/js/libs/__init__.py
NetkillerArchitectFix1/js/libs/jquery.min.js
NetkillerArchitectFix1/js/libs/localforage.min.js
NetkillerArchitectFix1/js/libs/screenfull.js
NetkillerArchitectFix1/js/libs/screenfull.min.js
NetkillerArchitectFix1/js/libs/zip.min.js
netkiller_architect_fix1-2025.3.24.0.dist-info/METADATA
netkiller_architect_fix1-2025.3.24.0.dist-info/WHEEL
netkiller_architect_fix1-2025.3.24.0.dist-info/entry_points.txt
netkiller_architect_fix1-2025.3.24.0.dist-info/top_level.txt
netkiller_architect_fix1-2025.3.24.0.dist-info/RECORD
